[
  {
    "id": "1",
    "courseCode": "01418111",
    "courseName": "Introduction to Computer Science",
    "grade": "B+",
    "credit": 2
  },
  {
    "id": "2",
    "courseCode": "01418141",
    "courseName": "Intellectual Properties and Professional Ethics",
    "grade": "B+",
    "credit": 3
  },
  {
    "id": "3",
    "courseCode": "01999021",
    "courseName": "Thai Language for Communication",
    "grade": "B",
    "credit": 3
  },
  {
    "id": "4",
    "courseCode": "01999111",
    "courseName": "Knowledge of the Land",
    "grade": "A",
    "credit": 2
  },
  {
    "id": "5",
    "courseCode": "03751112",
    "courseName": "Social and Politics",
    "grade": "B",
    "credit": 3
  },
  {
    "id": "6",
    "courseCode": "01355101",
    "courseName": "English for Everyday Life",
    "grade": "A",
    "credit": 3
  },
  {
    "id": "7",
    "courseCode": "01417111",
    "courseName": "Calculus I",
    "grade": "A",
    "credit": 3
  },
  {
    "id": "8",
    "courseCode": "01418112",
    "courseName": "Fundamental Programming Concepts",
    "grade": "A",
    "credit": 3
  },
  {
    "id": "9",
    "courseCode": "01418112",
    "courseName": "Basic Linear Algebra",
    "grade": "A",
    "credit": 3
  },
  {
    "id": "10",
    "courseCode": "01999041",
    "courseName": "Economics for Better Living",
    "grade": "C",
    "credit": 3
  },
  {
    "id": "11",
    "courseCode": "01418132",
    "courseName": "Fundamentals of Computing",
    "grade": "A",
    "credit": 3
  },
  {
    "id": "12",
    "courseCode": "01175163",
    "courseName": "Golf for Health",
    "grade": "A",
    "credit": 1
  },
  {
    "id": "13",
    "courseCode": "01418113",
    "courseName": "Computer Programming",
    "grade": "A",
    "credit": 3
  },
  {
    "id": "14",
    "courseCode": "01355102",
    "courseName": "English for University Life",
    "grade": "B+",
    "credit": 3
  },
  {
    "id": "15",
    "courseCode": "03654111",
    "courseName": "Aesthetics of Sport",
    "grade": "A",
    "credit": 3
  },
  {
    "id": "16",
    "courseCode": "01418131",
    "courseName": "Statistical Programming",
    "grade": "A",
    "credit": 3
  },
  {
    "id": "17",
    "courseCode": "01418361",
    "courseName": "Introduction to Computer Vision",
    "grade": "A",
    "credit": 3
  },
  {
    "id": "18",
    "courseCode": "01418211",
    "courseName": "Software Construction",
    "grade": "A",
    "credit": 3
  },
  {
    "id": "19",
    "courseCode": "01999012",
    "courseName": "Health for Life",
    "grade": "A",
    "credit": 3
  },
  {
    "id": "20",
    "courseCode": "01418231",
    "courseName": "Data Structures and Algorithms",
    "grade": "A",
    "credit": 3
  },
  {
    "id": "21",
    "courseCode": "01418233",
    "courseName": "Computer Architecture",
    "grade": "A",
    "credit": 3
  },
  {
    "id": "22",
    "courseCode": "01174231",
    "courseName": "Introduction to Recreation",
    "grade": "B",
    "credit": 2
  }
]